exspec/__init__.py
exspec/deflattener.py
exspec/example.py
exspec/grammar.py
exspec/models.py
exspec/operations.py
exspec/parser.py
exspec/utils.py
exspec-0.1.0.dist-info/LICENSE
exspec-0.1.0.dist-info/METADATA
exspec-0.1.0.dist-info/WHEEL
exspec-0.1.0.dist-info/top_level.txt
exspec-0.1.0.dist-info/RECORD
