Metadata-Version: 2.1
Name: exspec
Version: 0.1.0
Summary: The ExSpec package provides tools to parse, manipulate, and analyze **experiment specifications with a custom grammar
Home-page: https://gitlab.rakshitmittal.net/mde/msdl/exspec
Author: Rakshit Mittal
Author-email: pypi@rakshitmittal.net
License: MIT
Classifier: Programming Language :: Python :: 3
Classifier: License :: OSI Approved :: MIT License
Classifier: Operating System :: OS Independent
Requires-Python: >=3.6
License-File: LICENSE
Requires-Dist: lark
